envoy/base/utils/__init__.py
envoy/base/utils/data_env.py
envoy/base/utils/data_env_cmd.py
envoy/base/utils/exceptions.py
envoy/base/utils/fetch_cmd.py
envoy/base/utils/fetch_runner.py
envoy/base/utils/interface.py
envoy/base/utils/jinja_env.py
envoy/base/utils/jinja_env_cmd.py
envoy/base/utils/parallel_cmd.py
envoy/base/utils/parallel_runner.py
envoy/base/utils/project.py
envoy/base/utils/project_cmd.py
envoy/base/utils/project_data_cmd.py
envoy/base/utils/project_runner.py
envoy/base/utils/protobuf.py
envoy/base/utils/py.typed
envoy/base/utils/tar.py
envoy/base/utils/typing.py
envoy/base/utils/utils.py
envoy/base/utils/yaml.py
envoy/base/utils/abstract/__init__.py
envoy/base/utils/abstract/protobuf.py
envoy/base/utils/abstract/project/__init__.py
envoy/base/utils/abstract/project/changelog.py
envoy/base/utils/abstract/project/inventory.py
envoy/base/utils/abstract/project/project.py
envoy.base.utils-0.5.11.dist-info/METADATA
envoy.base.utils-0.5.11.dist-info/WHEEL
envoy.base.utils-0.5.11.dist-info/entry_points.txt
envoy.base.utils-0.5.11.dist-info/namespace_packages.txt
envoy.base.utils-0.5.11.dist-info/top_level.txt
envoy.base.utils-0.5.11.dist-info/RECORD
