Metadata-Version: 2.1
Name: envoy.base.utils
Version: 0.5.11
Summary: "A collection of utils used in Envoy proxy's CI"
Home-page: https://github.com/envoyproxy/toolshed/tree/main/envoy.base.utils
Author: Ryan Northey
Author-email: ryan@synca.io
Maintainer: Ryan Northey
Maintainer-email: ryan@synca.io
License: Apache Software License 2.0
Requires-Python: >=3.11.0
Requires-Dist: abstracts (>=0.0.12)
Requires-Dist: aio.api.github (>=0.2.10)
Requires-Dist: aio.core (>=0.10.5)
Requires-Dist: aio.run.runner (>=0.3.4)
Requires-Dist: aiohttp (>=3.11.6)
Requires-Dist: frozendict
Requires-Dist: jinja2 (>=3.1.4)
Requires-Dist: orjson
Requires-Dist: packaging (>=23.0)
Requires-Dist: protobuf (>=5.29.5)
Requires-Dist: python-gnupg
Requires-Dist: pytz
Requires-Dist: pyyaml
Requires-Dist: trycast (>=0.7.3)
Requires-Dist: types-protobuf
Requires-Dist: types-pytz
Requires-Dist: zstandard
